constrainedmf/__init__.py
constrainedmf/_version.py
constrainedmf/nmf/__init__.py
constrainedmf/nmf/metrics.py
constrainedmf/nmf/models.py
constrainedmf/nmf/utils.py
constrainedmf/tests/__init__.py
constrainedmf/tests/conftest.py
constrainedmf/tests/test_nmf.py
constrainedmf/utils/__init__.py
constrainedmf/utils/plotting.py
constrainedmf/wrappers/__init__.py
constrainedmf/wrappers/scattering.py
example_scripts/__init__.py
example_scripts/bto.py
example_scripts/fixing_components.py
example_scripts/fixing_weights.py
example_scripts/molten_salt.py
constrained_matrix_factorization-0.1.2.dist-info/AUTHORS.rst
constrained_matrix_factorization-0.1.2.dist-info/LICENSE
constrained_matrix_factorization-0.1.2.dist-info/METADATA
constrained_matrix_factorization-0.1.2.dist-info/WHEEL
constrained_matrix_factorization-0.1.2.dist-info/entry_points.txt
constrained_matrix_factorization-0.1.2.dist-info/top_level.txt
constrained_matrix_factorization-0.1.2.dist-info/RECORD
