Metadata-Version: 2.1
Name: constrained-matrix-factorization
Version: 0.1.2
Summary: Advancements on non-negative matrix factorization in PyTorch, with crystallography as a primary use case.
Home-page: https://github.com/NSLS-II/constrained-matrix-factorization
Author: Phil Maffettone
Author-email: pmaffettone@bnl.gov
License: BSD (3-clause)
Platform: UNKNOWN
Classifier: Development Status :: 2 - Pre-Alpha
Classifier: Natural Language :: English
Classifier: Programming Language :: Python :: 3
Requires-Python: >=3.7
License-File: LICENSE
License-File: AUTHORS.rst
Requires-Dist: torch
Requires-Dist: numpy
Requires-Dist: scipy
